{"paperId": "892817a6837e462dfcc8daa948cee58aa6481f0e", "externalIds": {"MAG": "1591132889", "DOI": "10.1108/ir.2010.04937eae.001"}, "url": "https://www.semanticscholar.org/paper/892817a6837e462dfcc8daa948cee58aa6481f0e", "title": "Wired for War: The Robotics Revolution and Conflict in the 21st Century", "abstract": "Dr. Singer is a person who likes to tackle provocative topics, and does so in a very engaging and instructive manner. Subjects such as child soldiers and military outsourcing are subjects of his previous award-winning books, both of which were discussed earlier at the Carnegie Council. The transcripts for his talks on Corporate Warriors and Children at War can be found by visiting our website at http://www.cceia.org/index.html.", "venue": "", "year": 2009, "referenceCount": 1, "citationCount": 427, "influentialCitationCount": 27, "isOpenAccess": false, "fieldsOfStudy": ["Engineering"], "authors": [{"authorId": "50776971", "name": "P. Singer"}]}