<rdf:RDF
 xmlns:rdf="http://www.w3.org/1999/02/22-rdf-syntax-ns#"
 xmlns:res="http://purl.org/vocab/resourcelist/schema#"
 xmlns:z="http://www.zotero.org/namespaces/export#"
 xmlns:dcterms="http://purl.org/dc/terms/"
 xmlns:bibo="http://purl.org/ontology/bibo/">
    <z:UserItem rdf:about="3DY57B8G">
        <res:resource rdf:resource="http://www.fenixedu.org"/>
        <z:accessDate>2021-05-09 03:35:03</z:accessDate>
    </z:UserItem>
    <bibo:Webpage rdf:about="http://www.fenixedu.org">
        <dcterms:title>FenixEdu™</dcterms:title>
        <bibo:uri>http://www.fenixedu.org</bibo:uri>
        <dcterms:abstract>FenixEdu Learning is an open-source academic information platform.</dcterms:abstract>
        <dcterms:language>pt_PT</dcterms:language>
        <dcterms:isPartOf>
           <bibo:Website><dcterms:title>FenixEdu</dcterms:title></bibo:Website>
        </dcterms:isPartOf>
    </bibo:Webpage>
</rdf:RDF>
