<rdf:RDF
 xmlns:rdf="http://www.w3.org/1999/02/22-rdf-syntax-ns#"
 xmlns:ctag="http://commontag.org/ns#"
 xmlns:z="http://www.zotero.org/namespaces/export#"
 xmlns:res="http://purl.org/vocab/resourcelist/schema#"
 xmlns:dcterms="http://purl.org/dc/terms/"
 xmlns:bibo="http://purl.org/ontology/bibo/"
 xmlns:foaf="http://xmlns.com/foaf/0.1/">
    <z:UserItem rdf:about="JE446J7N">
        <ctag:tagged>
            <ctag:AutoTag>
               <ctag:label>Translation and Interpreters</ctag:label>
            </ctag:AutoTag>
        </ctag:tagged>
        <z:repository>NYTimes.com</z:repository>
        <z:accessDate>2021-03-21 06:01:21</z:accessDate>
        <ctag:tagged>
            <ctag:AutoTag>
               <ctag:label>Artificial Intelligence</ctag:label>
            </ctag:AutoTag>
        </ctag:tagged>
        <ctag:tagged>
            <ctag:AutoTag>
               <ctag:label>Lewis-Kraus, Gideon</ctag:label>
            </ctag:AutoTag>
        </ctag:tagged>
        <res:resource rdf:resource="https://www.nytimes.com/2016/12/14/magazine/the-great-ai-awakening.html"/>
        <ctag:tagged>
           <ctag:AutoTag><ctag:label>Google Inc</ctag:label></ctag:AutoTag>
        </ctag:tagged>
        <ctag:tagged>
           <ctag:AutoTag><ctag:label>Pichai, Sundar</ctag:label></ctag:AutoTag>
        </ctag:tagged>
        <ctag:tagged>
            <ctag:AutoTag>
               <ctag:label>Voice Recognition Systems</ctag:label>
            </ctag:AutoTag>
        </ctag:tagged>
        <ctag:tagged>
            <ctag:AutoTag>
               <ctag:label>Computers and the Internet</ctag:label>
            </ctag:AutoTag>
        </ctag:tagged>
        <ctag:tagged>
            <ctag:AutoTag>
               <ctag:label>Dean, Jeff (1968- )</ctag:label>
            </ctag:AutoTag>
        </ctag:tagged>
        <ctag:tagged>
            <ctag:AutoTag>
               <ctag:label>Hinton, Geoffrey E</ctag:label>
            </ctag:AutoTag>
        </ctag:tagged>
    </z:UserItem>
    <bibo:Article rdf:about="https://www.nytimes.com/2016/12/14/magazine/the-great-ai-awakening.html">
        <dcterms:title>The Great A.I. Awakening</dcterms:title>
        <bibo:section>Magazine</bibo:section>
        <bibo:uri>https://www.nytimes.com/2016/12/14/magazine/the-great-ai-awakening.html</bibo:uri>
        <dcterms:abstract>How Google used artificial intelligence to transform Google Translate, one of its more popular services — and how machine learning is poised to reinvent computing itself.</dcterms:abstract>
        <dcterms:language>en-US</dcterms:language>
        <dcterms:creator rdf:nodeID="n592"/>
        <bibo:authorList>
           <rdf:Seq><rdf:li rdf:nodeID="n592"/></rdf:Seq>
        </bibo:authorList>
        <dcterms:isPartOf>
            <bibo:Issue>
                <dcterms:date>2016-12-14</dcterms:date>
                <dcterms:isPartOf>
                    <bibo:Newspaper>
                        <dcterms:title>The New York Times</dcterms:title>
                        <bibo:issn>0362-4331</bibo:issn>
                    </bibo:Newspaper>
                </dcterms:isPartOf>
            </bibo:Issue>
        </dcterms:isPartOf>
    </bibo:Article>
    <foaf:Person rdf:nodeID="n592">
        <foaf:givenName>Gideon</foaf:givenName>
        <foaf:surname>Lewis-Kraus</foaf:surname>
    </foaf:Person>
</rdf:RDF>
