<rdf:RDF
 xmlns:rdf="http://www.w3.org/1999/02/22-rdf-syntax-ns#"
 xmlns:res="http://purl.org/vocab/resourcelist/schema#"
 xmlns:z="http://www.zotero.org/namespaces/export#"
 xmlns:bibo="http://purl.org/ontology/bibo/"
 xmlns:dcterms="http://purl.org/dc/terms/">
    <z:UserItem rdf:about="K2CHBUQH">
        <res:resource rdf:resource="https://accounts.google.com/ServiceLogin?service=wise&amp;passive=1209600&amp;continue=https://drive.google.com/file/d/1BEg2ZH_2BUKgfnuYYNj-rs3c29jiMOgi/view?usp%253Ddrive_open&amp;followup=https://drive.google.com/file/d/1BEg2ZH_2BUKgfnuYYNj-rs3c29jiMOgi/view?usp%253Ddrive_open&amp;ec=GAZAGQ"/>
        <z:accessDate>2021-05-09 03:11:54</z:accessDate>
    </z:UserItem>
    <bibo:Webpage rdf:about="https://accounts.google.com/ServiceLogin?service=wise&amp;passive=1209600&amp;continue=https://drive.google.com/file/d/1BEg2ZH_2BUKgfnuYYNj-rs3c29jiMOgi/view?usp%253Ddrive_open&amp;followup=https://drive.google.com/file/d/1BEg2ZH_2BUKgfnuYYNj-rs3c29jiMOgi/view?usp%253Ddrive_open&amp;ec=GAZAGQ">
        <bibo:uri>https://accounts.google.com/ServiceLogin?service=wise&amp;passive=1209600&amp;continue=https://drive.google.com/file/d/1BEg2ZH_2BUKgfnuYYNj-rs3c29jiMOgi/view?usp%3Ddrive_open&amp;followup=https://drive.google.com/file/d/1BEg2ZH_2BUKgfnuYYNj-rs3c29jiMOgi/view?usp%3Ddrive_open&amp;ec=GAZAGQ</bibo:uri>
        <dcterms:title>Google Drive: Sign-in</dcterms:title>
        <dcterms:abstract>Access Google Drive with a free Google account (for personal use) or Google Workspace account (for business use).</dcterms:abstract>
    </bibo:Webpage>
</rdf:RDF>
