<rdf:RDF
 xmlns:rdf="http://www.w3.org/1999/02/22-rdf-syntax-ns#"
 xmlns:res="http://purl.org/vocab/resourcelist/schema#"
 xmlns:z="http://www.zotero.org/namespaces/export#"
 xmlns:dcterms="http://purl.org/dc/terms/"
 xmlns:bibo="http://purl.org/ontology/bibo/"
 xmlns:foaf="http://xmlns.com/foaf/0.1/">
    <z:UserItem rdf:about="K7F423I5">
        <res:resource rdf:resource="https://www.academia.edu/37342574/Syllabus_The_Gospel_of_John_and_its_Earliest_Readers_UNC_Chapel_Hill_2020_update_"/>
        <z:repository>www.academia.edu</z:repository>
        <z:accessDate>2021-05-09 03:49:35</z:accessDate>
    </z:UserItem>
    <bibo:AcademicArticle rdf:about="https://www.academia.edu/37342574/Syllabus_The_Gospel_of_John_and_its_Earliest_Readers_UNC_Chapel_Hill_2020_update_">
        <dcterms:title>Syllabus: &amp;quot;The Gospel of John and its Earliest Readers&amp;quot; (UNC Chapel Hill, 2020 update)</dcterms:title>
        <bibo:uri>https://www.academia.edu/37342574/Syllabus_The_Gospel_of_John_and_its_Earliest_Readers_UNC_Chapel_Hill_2020_update_</bibo:uri>
        <dcterms:language>en</dcterms:language>
        <bibo:shortTitle>Syllabus</bibo:shortTitle>
        <dcterms:creator rdf:nodeID="n9254"/>
        <bibo:authorList>
           <rdf:Seq><rdf:li rdf:nodeID="n9254"/></rdf:Seq>
        </bibo:authorList>
    </bibo:AcademicArticle>
    <foaf:Person rdf:nodeID="n9254">
       <foaf:givenName>Hugo</foaf:givenName><foaf:surname>Méndez</foaf:surname>
    </foaf:Person>
</rdf:RDF>
