<rdf:RDF
 xmlns:rdf="http://www.w3.org/1999/02/22-rdf-syntax-ns#"
 xmlns:res="http://purl.org/vocab/resourcelist/schema#"
 xmlns:z="http://www.zotero.org/namespaces/export#"
 xmlns:dcterms="http://purl.org/dc/terms/"
 xmlns:bibo="http://purl.org/ontology/bibo/"
 xmlns:sioct="http://rdfs.org/sioc/types#">
    <z:UserItem rdf:about="Y8QKYY3L">
        <res:resource rdf:resource="https://musicmachinery.com/2011/05/14/how-good-is-googles-instant-mix/"/>
        <z:accessDate>2021-05-09 03:14:02</z:accessDate>
    </z:UserItem>
    <sioct:BlogPost rdf:about="https://musicmachinery.com/2011/05/14/how-good-is-googles-instant-mix/">
        <dcterms:title>How good is Google’s Instant Mix?</dcterms:title>
        <bibo:uri>https://musicmachinery.com/2011/05/14/how-good-is-googles-instant-mix/</bibo:uri>
        <dcterms:abstract>This week, Google launched the beta of its music locker service where you can upload all your music to the cloud and listen to it from anywhere.   According to Techcrunch, Google’s Paul Joyce…</dcterms:abstract>
        <dcterms:language>en</dcterms:language>
        <rdf:type rdf:resource="http://purl.org/ontology/bibo/Article"/>
        <dcterms:isPartOf>
            <sioct:Weblog>
                <dcterms:title>Music Machinery</dcterms:title>
                <dcterms:date>2011-05-14T15:26:59+00:00</dcterms:date>
                <rdf:type rdf:resource="http://purl.org/ontology/bibo/Website"/>
            </sioct:Weblog>
        </dcterms:isPartOf>
    </sioct:BlogPost>
</rdf:RDF>
