<rdf:RDF
 xmlns:rdf="http://www.w3.org/1999/02/22-rdf-syntax-ns#"
 xmlns:res="http://purl.org/vocab/resourcelist/schema#"
 xmlns:z="http://www.zotero.org/namespaces/export#"
 xmlns:dcterms="http://purl.org/dc/terms/"
 xmlns:bibo="http://purl.org/ontology/bibo/">
    <z:UserItem rdf:about="YUW7A6CC">
        <res:resource rdf:resource="https://www.law.berkeley.edu/research/bclt/students/law-technology-certificate-program/"/>
        <z:accessDate>2021-05-09 03:54:38</z:accessDate>
    </z:UserItem>
    <bibo:Webpage rdf:about="https://www.law.berkeley.edu/research/bclt/students/law-technology-certificate-program/">
        <dcterms:title>Law &amp; Technology Certificate Program</dcterms:title>
        <bibo:uri>https://www.law.berkeley.edu/research/bclt/students/law-technology-certificate-program/</bibo:uri>
        <dcterms:abstract>BCLT offers the nation’s leading program in law and technology. The Law &amp; Technology Certificate recognizes successful completion of a focused course of study, including writing and student activity components. The curricular requirements emphasize depth and breadth of coverage but also afford students substantial flexibility in adapting their course of study toward a range of career […]</dcterms:abstract>
        <dcterms:language>en-US</dcterms:language>
        <dcterms:isPartOf>
            <bibo:Website>
               <dcterms:title>Berkeley Law</dcterms:title>
            </bibo:Website>
        </dcterms:isPartOf>
    </bibo:Webpage>
</rdf:RDF>
